med/__init__.py
med/__main__.py
med/base.py
med/cli.py
med/constants.py
mwiszenko_med-1.0.1.dist-info/LICENSE
mwiszenko_med-1.0.1.dist-info/METADATA
mwiszenko_med-1.0.1.dist-info/WHEEL
mwiszenko_med-1.0.1.dist-info/entry_points.txt
mwiszenko_med-1.0.1.dist-info/top_level.txt
mwiszenko_med-1.0.1.dist-info/RECORD
